libpagure/__init__.py
libpagure/exceptions.py
libpagure/libpagure.py
libpagure-0.22.dist-info/LICENSE.txt
libpagure-0.22.dist-info/METADATA
libpagure-0.22.dist-info/WHEEL
libpagure-0.22.dist-info/top_level.txt
libpagure-0.22.dist-info/RECORD
