Metadata-Version: 2.1
Name: libpagure
Version: 0.22
Summary: A Python library for Pagure APIs.
Home-page: https://github.com/yangl1996/libpagure
Author: Lei Yang
Author-email: yltt1234512@gmail.com
License: GNU General Public License v2.0
Keywords: pagure,api,library
Platform: UNKNOWN
Classifier: Development Status :: 3 - Alpha
Classifier: Intended Audience :: Developers
Classifier: Intended Audience :: Information Technology
Classifier: License :: OSI Approved :: GNU General Public License v2 or later (GPLv2+)
Classifier: Programming Language :: Python
Classifier: Programming Language :: Python :: 2
Classifier: Programming Language :: Python :: 2.6
Classifier: Programming Language :: Python :: 2.7
Classifier: Programming Language :: Python :: 3
Classifier: Topic :: Software Development :: Libraries
Requires-Dist: requests
